pyvider/__init__.py
pyvider/components/__init__.py
pyvider/components/_version.py
pyvider/components/capabilities/__init__.py
pyvider/components/capabilities/api.py
pyvider/components/capabilities/lens.py
pyvider/components/data_sources/__init__.py
pyvider/components/data_sources/env_variables.py
pyvider/components/data_sources/file_info.py
pyvider/components/data_sources/http_api.py
pyvider/components/data_sources/lens_jq.py
pyvider/components/data_sources/nested_data_test_suite.py
pyvider/components/data_sources/provider_config_reader.py
pyvider/components/data_sources/env_variables.plating/docs/pyvider_env_variables.tmpl.md
pyvider/components/data_sources/env_variables.plating/examples/basic.tf
pyvider/components/data_sources/env_variables.plating/examples/filtering.tf
pyvider/components/data_sources/env_variables.plating/examples/multi_environment.tf
pyvider/components/data_sources/env_variables.plating/examples/sensitive.tf
pyvider/components/data_sources/file_info.plating/docs/pyvider_file_info.tmpl.md
pyvider/components/data_sources/file_info.plating/examples/basic.tf
pyvider/components/data_sources/http_api.plating/docs/pyvider_http_api.tmpl.md
pyvider/components/data_sources/http_api.plating/examples/advanced.tf
pyvider/components/data_sources/http_api.plating/examples/basic.tf
pyvider/components/data_sources/lens_jq.plating/docs/pyvider_lens_jq.tmpl.md
pyvider/components/data_sources/lens_jq.plating/examples/api_processing.tf
pyvider/components/data_sources/lens_jq.plating/examples/basic.tf
pyvider/components/data_sources/lens_jq.plating/examples/complex.tf
pyvider/components/data_sources/nested_data_test_suite.plating/docs/main.md.j2
pyvider/components/data_sources/nested_data_test_suite.plating/docs/nested_data_test_suite.tmpl.md
pyvider/components/data_sources/nested_data_test_suite.plating/examples/basic.tf
pyvider/components/data_sources/nested_data_test_suite.plating/examples/example.tf
pyvider_components-0.0.1000.dist-info/METADATA
pyvider_components-0.0.1000.dist-info/WHEEL
pyvider_components-0.0.1000.dist-info/top_level.txt
pyvider_components-0.0.1000.dist-info/RECORD
