Metadata-Version: 2.4
Name: pyvider-components
Version: 0.0.1000
Summary: Standard Components for the Pyvider Framework
Requires-Python: >=3.11
Requires-Dist: provide-foundation
Requires-Dist: pyvider-rpcplugin
Requires-Dist: httpx>=0.28.1
Requires-Dist: jq>=1.9.1
Requires-Dist: jinja2>=3.1.6
Requires-Dist: pyvider-cty>=0.0.113
Requires-Dist: pyvider>=0.0.0.post0
Requires-Dist: plating
